JingtongTensorflow1XChuyiFix1/README.md
JingtongTensorflow1XChuyiFix1/__init__.py
JingtongTensorflow1XChuyiFix1/__main__.py
JingtongTensorflow1XChuyiFix1/file.epub
JingtongTensorflow1XChuyiFix1/index.html
JingtongTensorflow1XChuyiFix1/css/__init__.py
JingtongTensorflow1XChuyiFix1/css/annotations.css
JingtongTensorflow1XChuyiFix1/css/main.css
JingtongTensorflow1XChuyiFix1/css/normalize.css
JingtongTensorflow1XChuyiFix1/css/popup.css
JingtongTensorflow1XChuyiFix1/font/__init__.py
JingtongTensorflow1XChuyiFix1/font/fontello.eot
JingtongTensorflow1XChuyiFix1/font/fontello.svg
JingtongTensorflow1XChuyiFix1/font/fontello.ttf
JingtongTensorflow1XChuyiFix1/font/fontello.woff
JingtongTensorflow1XChuyiFix1/img/__init__.py
JingtongTensorflow1XChuyiFix1/img/annotator-glyph-sprite.png
JingtongTensorflow1XChuyiFix1/img/annotator-icon-sprite.png
JingtongTensorflow1XChuyiFix1/img/apple-touch-icon.png
JingtongTensorflow1XChuyiFix1/img/cancelfullscreen.png
JingtongTensorflow1XChuyiFix1/img/close.png
JingtongTensorflow1XChuyiFix1/img/fullscreen.png
JingtongTensorflow1XChuyiFix1/img/loader.gif
JingtongTensorflow1XChuyiFix1/img/menu-icon.png
JingtongTensorflow1XChuyiFix1/img/save.png
JingtongTensorflow1XChuyiFix1/img/saved.png
JingtongTensorflow1XChuyiFix1/img/settings-s.png
JingtongTensorflow1XChuyiFix1/img/settings.png
JingtongTensorflow1XChuyiFix1/img/star.png
JingtongTensorflow1XChuyiFix1/js/__init__.py
JingtongTensorflow1XChuyiFix1/js/epub.js
JingtongTensorflow1XChuyiFix1/js/epub.min.js
JingtongTensorflow1XChuyiFix1/js/epub.min.map
JingtongTensorflow1XChuyiFix1/js/hooks.min.js
JingtongTensorflow1XChuyiFix1/js/hooks.min.map
JingtongTensorflow1XChuyiFix1/js/reader.js
JingtongTensorflow1XChuyiFix1/js/reader.js.map
JingtongTensorflow1XChuyiFix1/js/reader.min.js
JingtongTensorflow1XChuyiFix1/js/reader.min.map
JingtongTensorflow1XChuyiFix1/js/hooks/__init__.py
JingtongTensorflow1XChuyiFix1/js/hooks/extensions/__init__.py
JingtongTensorflow1XChuyiFix1/js/hooks/extensions/highlight.js
jingtong_tensorflow_1_x_chuyi_fix1-2025.3.24.0.dist-info/METADATA
jingtong_tensorflow_1_x_chuyi_fix1-2025.3.24.0.dist-info/WHEEL
jingtong_tensorflow_1_x_chuyi_fix1-2025.3.24.0.dist-info/entry_points.txt
jingtong_tensorflow_1_x_chuyi_fix1-2025.3.24.0.dist-info/top_level.txt
jingtong_tensorflow_1_x_chuyi_fix1-2025.3.24.0.dist-info/RECORD
